{
  "main": {
    "id": "afc3fe0383aebaf5",
    "type": "split",
    "children": [
      {
        "id": "13b1b80a3a92242b",
        "type": "tabs",
        "children": [
          {
            "id": "91bff7d994216169",
            "type": "leaf",
            "state": {
              "type": "markdown",
              "state": {
                "file": "Computer_Science/Machine_Learning/EECS16B/Module1_Signal_Processing/Advanced_Circuit_Elements/Capacitors&Inductors&OpAmp.md",
                "mode": "source",
                "source": false
              }
            }
          }
        ]
      }
    ],
    "direction": "vertical"
  },
  "left": {
    "id": "f900f31b8b407685",
    "type": "split",
    "children": [
      {
        "id": "ac58ecdddeed7005",
        "type": "tabs",
        "dimension": 65.43715846994536,
        "children": [
          {
            "id": "932953190040c9d5",
            "type": "leaf",
            "state": {
              "type": "file-explorer",
              "state": {
                "sortOrder": "alphabetical"
              }
            }
          },
          {
            "id": "a1ae5d442675c9de",
            "type": "leaf",
            "state": {
              "type": "search",
              "state": {
                "query": "member initial",
                "matchingCase": false,
                "explainSearch": false,
                "collapseAll": false,
                "extraContext": false,
                "sortOrder": "alphabetical"
              }
            }
          },
          {
            "id": "f77f76cb311858e9",
            "type": "leaf",
            "state": {
              "type": "starred",
              "state": {}
            }
          },
          {
            "id": "eae0deb31a4dd2bb",
            "type": "leaf",
            "state": {
              "type": "bookmarks",
              "state": {}
            }
          }
        ]
      },
      {
        "id": "4f417f835f612f94",
        "type": "tabs",
        "dimension": 34.56284153005464,
        "children": [
          {
            "id": "f58fc5649c2dc1e2",
            "type": "leaf",
            "state": {
              "type": "recent-files",
              "state": {}
            }
          }
        ]
      }
    ],
    "direction": "horizontal",
    "width": 362.50152587890625
  },
  "right": {
    "id": "646448ef3be5aeb8",
    "type": "split",
    "children": [
      {
        "id": "a57d72b1463cfa44",
        "type": "tabs",
        "dimension": 46.018893387314435,
        "children": [
          {
            "id": "abd22396395eb00b",
            "type": "leaf",
            "state": {
              "type": "quiet-outline",
              "state": {}
            }
          },
          {
            "id": "2bfcad073fc70b2f",
            "type": "leaf",
            "state": {
              "type": "advanced-tables-toolbar",
              "state": {}
            }
          }
        ]
      },
      {
        "id": "ac5e674590e10608",
        "type": "tabs",
        "dimension": 26.990553306342782,
        "children": [
          {
            "id": "83c7969190d88bc2",
            "type": "leaf",
            "state": {
              "type": "backlink",
              "state": {
                "file": "Computer_Science/Machine_Learning/EECS16B/Module1_Signal_Processing/Advanced_Circuit_Elements/Capacitors&Inductors&OpAmp.md",
                "collapseAll": false,
                "extraContext": false,
                "sortOrder": "alphabetical",
                "showSearch": false,
                "searchQuery": "",
                "backlinkCollapsed": false,
                "unlinkedCollapsed": true
              }
            }
          },
          {
            "id": "4b87139d7043d916",
            "type": "leaf",
            "state": {
              "type": "outgoing-link",
              "state": {
                "file": "Computer_Science/Machine_Learning/EECS16B/Module1_Signal_Processing/Advanced_Circuit_Elements/Capacitors&Inductors&OpAmp.md",
                "linksCollapsed": false,
                "unlinkedCollapsed": true
              }
            }
          }
        ],
        "currentTab": 1
      },
      {
        "id": "2349a3933801eec4",
        "type": "tabs",
        "dimension": 26.990553306342782,
        "children": [
          {
            "id": "06e519aa4232ea63",
            "type": "leaf",
            "state": {
              "type": "tag",
              "state": {
                "sortOrder": "frequency",
                "useHierarchy": true
              }
            }
          },
          {
            "id": "2ad6c65501c7e27e",
            "type": "leaf",
            "state": {
              "type": "calendar",
              "state": {}
            }
          }
        ],
        "currentTab": 1
      }
    ],
    "direction": "horizontal",
    "width": 200
  },
  "left-ribbon": {
    "hiddenItems": {
      "switcher:Open quick switcher": false,
      "graph:Open graph view": false,
      "canvas:Create new canvas": false,
      "daily-notes:Open today's daily note": false,
      "templates:Insert template": false,
      "command-palette:Open command palette": false,
      "workspaces:Manage workspace layouts": false,
      "obsidian-excalidraw-plugin:Create new drawing": false,
      "table-editor-obsidian:Advanced Tables Toolbar": false,
      "oz-clear-unused-images:Clear Unused Images": false,
      "obsidian-custom-frames:Open Notion": false,
      "obsidian-custom-frames:Open Google Calendar": false,
      "templater-obsidian:Templater": false
    }
  },
  "active": "91bff7d994216169",
  "lastOpenFiles": [
    "Computer_Science/Machine_Learning/EECS16B/Module1_Signal_Processing/Advanced_Circuit_Elements/Transistors&Logics.md",
    "Computer_Science/Machine_Learning/EECS16B/Module1_Signal_Processing/Advanced_Circuit_Elements/Complex_Arithmetic_I.md",
    "Computer_Science/Machine_Learning/EECS16B/Module1_Signal_Processing/Advanced_Circuit_Elements/Capacitors&Inductors&OpAmp.md",
    "Computer_Science/Machine_Learning/EECS16B/Module2_Robotic_Control/Upper_Triangulation_Schur_Decomposition.md",
    "Computer_Science/Machine_Learning/EECS16B/Related_Resources.md",
    "Computer_Science/Machine_Learning/EECS16B/Module1_Signal_Processing/Labs/_Debugging_Circuits.md",
    "Computer_Science/Machine_Learning/EECS16B/Module1_Signal_Processing/Labs/_Motion_ S1XT33N.md",
    "Computer_Science/Machine_Learning/EECS16B/Module1_Signal_Processing/Labs/_Filters_Design.md",
    "Computer_Science/Machine_Learning/EECS16B/Module1_Signal_Processing/Homeworks/Homeworks_3_4.md",
    "Computer_Science/Machine_Learning/EECS16B/Module1_Signal_Processing/Homeworks/Homeworks_1_2.md",
    "Computer_Science/Machine_Learning/EECS16B/Module1_Signal_Processing/Differential_Equations-DC/High_Order_DEs.md",
    "Computer_Science/Machine_Learning/EECS16B/Module1_Signal_Processing/Differential_Equations-AC/_disc05B+disc06+HW6.md",
    "Computer_Science/Machine_Learning/EECS16B/Module1_Signal_Processing/Differential_Equations-AC/_Rational_Transfer_Functions.md",
    "Computer_Science/Machine_Learning/EECS16B/Module1_Signal_Processing/Differential_Equations-AC/_Circuit_Design_Principles.md",
    "Computer_Science/Machine_Learning/EECS16B/Module1_Signal_Processing/Differential_Equations-AC/Resonant_Circuits.md",
    "Computer_Science/Machine_Learning/EECS16B/Module1_Signal_Processing/Differential_Equations-AC/Filters&Bode_Plots.md",
    "Computer_Science/Machine_Learning/EECS16B/Module1_Signal_Processing/Differential_Equations-AC/_AC_Circuit_Analysis.md",
    "Computer_Science/Machine_Learning/EECS16B/Module1_Signal_Processing/Differential_Equations-AC/Phasor&Transfer_Functions.md",
    "Computer_Science/Machine_Learning/EECS16B/Module1_Signal_Processing/Differential_Equations-DC/Circuit_State_Anaysis.md",
    "Computer_Science/Machine_Learning/EECS16B/Module1_Signal_Processing/Differential_Equations-DC/Vector_DEs.md",
    "Computer_Science/Machine_Learning/EECS16B/Module1_Signal_Processing/Differential_Equations-DC/Basic_DEs.md",
    "Computer_Science/Machine_Learning/EECS16B/Module2_Robotic_Control/Transistors&Logics.assets",
    "Computer_Science/Machine_Learning/EECS16B/Module2_Robotic_Control/Stability_Feedback_Control.md",
    "Mathematics/Differential_Equations/MIT_18.03SC/3.7_Laplace_Transform.md",
    "Computer_Science/Machine_Learning/EECS16B/Module1_Signal_Processing/Labs/OpAmp_Basics.md",
    "Computer_Science/Machine_Learning/EECS16B/Module1_Signal_Processing/Homeworks",
    "Computer_Science/Machine_Learning/EECS16B/Module1_Signal_Processing/Differential_Equations-AC",
    "Computer_Science/Machine_Learning/EECS16B/Module1_Signal_Processing/Differential_Equations-DC",
    "Computer_Science/Machine_Learning/EECS16B/Module1_Signal_Processing/Advanced_Circuit_Elements",
    "Computer_Science/Machine_Learning/EECS16B/Module1_Signal_Processing/Labs/DAC_ADC.md",
    "Mathematics/Differential_Equations/MIT_18.031/Untitled.md",
    "Mathematics/Differential_Equations/MIT_18.031",
    "Computer_Science/Machine_Learning/EECS126/1_Probability_Review/Concentration_Inequalities.assets/image-20240126220854410.png",
    "Computer_Science/Machine_Learning/EECS126/1_Probability_Review/Concentration_Inequalities.assets/image-20240126220850345.png",
    "Computer_Science/Machine_Learning/EECS126/1_Probability_Review/Concentration_Inequalities.assets/image-20240126220132498.png",
    "Computer_Science/Machine_Learning/EECS126/1_Probability_Review/Concentration_Inequalities.assets/image-20240126220124239.png",
    "Computer_Science/Machine_Learning/EECS126/1_Probability_Review/Concentration_Inequalities.assets/image-20240126212941709.png",
    "Computer_Science/Machine_Learning/EECS126/1_Probability_Review/Concentration_Inequalities.assets/image-20240126212724162.png",
    "Computer_Science/Machine_Learning/EECS126/1_Probability_Review/Concentration_Inequalities.assets/image-20240126212714417.png",
    "Computer_Science/Machine_Learning/EECS126/1_Probability_Review/Concentration_Inequalities.assets/image-20240126212651711.png",
    "Computer_Science/Machine_Learning/EECS126/1_Probability_Review/Concentration_Inequalities.assets/image-20240126212536464.png",
    "Computer_Science/Machine_Learning/EECS126/1_Probability_Review/Concentration_Inequalities.assets",
    "Computer_Science/Machine_Learning/EECS126/1_Probability_Review/Probability Formulas and Theorems.assets/image-20240126160438269.png",
    "Computer_Science/Machine_Learning/EECS126/1_Probability_Review/Information_Theory.assets",
    "Computer_Science/Web_Development/Vue",
    "Computer_Science/Web_Development/React",
    "未命名.canvas"
  ]
}