{
  "main": {
    "id": "afc3fe0383aebaf5",
    "type": "split",
    "children": [
      {
        "id": "09e2d5737a212bdb",
        "type": "tabs",
        "children": [
          {
            "id": "7ff9fc9aee69b18c",
            "type": "leaf",
            "state": {
              "type": "markdown",
              "state": {
                "file": "Mathematics/NYU_Master_Program/DS-GA-1012_NLP/Lab_Notes/Lab1_Notes.md",
                "mode": "source",
                "source": false
              }
            }
          }
        ]
      }
    ],
    "direction": "vertical"
  },
  "left": {
    "id": "f900f31b8b407685",
    "type": "split",
    "children": [
      {
        "id": "ac58ecdddeed7005",
        "type": "tabs",
        "dimension": 65.43715846994536,
        "children": [
          {
            "id": "932953190040c9d5",
            "type": "leaf",
            "state": {
              "type": "file-explorer",
              "state": {
                "sortOrder": "alphabetical"
              }
            }
          },
          {
            "id": "a1ae5d442675c9de",
            "type": "leaf",
            "state": {
              "type": "search",
              "state": {
                "query": "member initial",
                "matchingCase": false,
                "explainSearch": false,
                "collapseAll": false,
                "extraContext": false,
                "sortOrder": "alphabetical"
              }
            }
          },
          {
            "id": "f77f76cb311858e9",
            "type": "leaf",
            "state": {
              "type": "starred",
              "state": {}
            }
          },
          {
            "id": "eae0deb31a4dd2bb",
            "type": "leaf",
            "state": {
              "type": "bookmarks",
              "state": {}
            }
          }
        ]
      },
      {
        "id": "4f417f835f612f94",
        "type": "tabs",
        "dimension": 34.56284153005464,
        "children": [
          {
            "id": "f58fc5649c2dc1e2",
            "type": "leaf",
            "state": {
              "type": "recent-files",
              "state": {}
            }
          }
        ]
      }
    ],
    "direction": "horizontal",
    "width": 200
  },
  "right": {
    "id": "646448ef3be5aeb8",
    "type": "split",
    "children": [
      {
        "id": "a57d72b1463cfa44",
        "type": "tabs",
        "dimension": 30,
        "children": [
          {
            "id": "abd22396395eb00b",
            "type": "leaf",
            "state": {
              "type": "quiet-outline",
              "state": {}
            }
          },
          {
            "id": "2bfcad073fc70b2f",
            "type": "leaf",
            "state": {
              "type": "advanced-tables-toolbar",
              "state": {}
            }
          }
        ]
      },
      {
        "id": "ac5e674590e10608",
        "type": "tabs",
        "dimension": 30.90277777777778,
        "children": [
          {
            "id": "83c7969190d88bc2",
            "type": "leaf",
            "state": {
              "type": "backlink",
              "state": {
                "file": "Mathematics/NYU_Master_Program/DS-GA-1012_NLP/Lab_Notes/Lab1_Notes.md",
                "collapseAll": false,
                "extraContext": false,
                "sortOrder": "alphabetical",
                "showSearch": false,
                "searchQuery": "",
                "backlinkCollapsed": false,
                "unlinkedCollapsed": true
              }
            }
          },
          {
            "id": "4b87139d7043d916",
            "type": "leaf",
            "state": {
              "type": "outgoing-link",
              "state": {
                "file": "Mathematics/NYU_Master_Program/DS-GA-1012_NLP/Lab_Notes/Lab1_Notes.md",
                "linksCollapsed": false,
                "unlinkedCollapsed": true
              }
            }
          }
        ],
        "currentTab": 1
      },
      {
        "id": "2349a3933801eec4",
        "type": "tabs",
        "dimension": 39.09722222222222,
        "children": [
          {
            "id": "06e519aa4232ea63",
            "type": "leaf",
            "state": {
              "type": "tag",
              "state": {
                "sortOrder": "frequency",
                "useHierarchy": true
              }
            }
          },
          {
            "id": "2ad6c65501c7e27e",
            "type": "leaf",
            "state": {
              "type": "calendar",
              "state": {}
            }
          }
        ],
        "currentTab": 1
      }
    ],
    "direction": "horizontal",
    "width": 292.5
  },
  "left-ribbon": {
    "hiddenItems": {
      "switcher:Open quick switcher": false,
      "graph:Open graph view": false,
      "canvas:Create new canvas": false,
      "daily-notes:Open today's daily note": false,
      "templates:Insert template": false,
      "command-palette:Open command palette": false,
      "workspaces:Manage workspace layouts": false,
      "obsidian-excalidraw-plugin:Create new drawing": false,
      "oz-clear-unused-images:Clear Unused Images": false,
      "table-editor-obsidian:Advanced Tables Toolbar": false,
      "obsidian-custom-frames:Open Notion": false,
      "obsidian-custom-frames:Open Google Calendar": false,
      "templater-obsidian:Templater": false
    }
  },
  "active": "7ff9fc9aee69b18c",
  "lastOpenFiles": [
    "Computer_Science/Information_Systems_Machine_Learning/EECS127AB/eecs127_reader.pdf.baiduyun.uploading.cfg",
    "Computer_Science/Information_Systems_Machine_Learning/EECS127AB/cvxbook-solutions.pdf.baiduyun.uploading.cfg",
    "Computer_Science/Information_Systems_Machine_Learning/EECS127AB/CEG-Optimization Models - Giuseppe C. Calafiore.pdf.baiduyun.uploading.cfg",
    "Computer_Science/Information_Systems_Machine_Learning/EECS127AB/BV_cvxbook.pdf.baiduyun.uploading.cfg",
    "Computer_Science/Information_Systems_Machine_Learning/EECS127AB/1_Linear_Algebra_Review/PCA_Low-rank_Approximation.assets/20231023_2309441598.png.baiduyun.uploading.cfg",
    "Computer_Science/Information_Systems_Machine_Learning/EECS127AB/1_Linear_Algebra_Review/PCA_Low-rank_Approximation.assets/20231023_2309422485.png.baiduyun.uploading.cfg",
    "Computer_Science/Information_Systems_Machine_Learning/EECS127AB/1_Linear_Algebra_Review/PCA_Low-rank_Approximation.assets/20231023_2309406607.png.baiduyun.uploading.cfg",
    "Computer_Science/Information_Systems_Machine_Learning/EECS127AB/1_Linear_Algebra_Review/PCA_Low-rank_Approximation.assets/20231023_2309386541.png.baiduyun.uploading.cfg",
    "Computer_Science/Information_Systems_Machine_Learning/EECS127AB/1_Linear_Algebra_Review/PCA_Low-rank_Approximation.assets/20231023_2309379079.png.baiduyun.uploading.cfg",
    "Computer_Science/Information_Systems_Machine_Learning/EECS127AB/1_Linear_Algebra_Review/PCA_Low-rank_Approximation.assets/20231023_2309355780.png.baiduyun.uploading.cfg",
    "Computer_Science/Information_Systems_Machine_Learning/EECS127AB/1_Linear_Algebra_Review/PCA_Low-rank_Approximation.assets/20231023_2309335541.png.baiduyun.uploading.cfg",
    "Computer_Science/Data_Structures_Algorithms/CS106B_X/6_OOP_Abstractions/Functions and Lambdas.md",
    "Mathematics/NYU_Master_Program/DS-GA-1012_NLP/Lab_Notes/Lab1_Notes.md",
    "Computer_Science/Information_Systems_Machine_Learning/EECS127AB/5_Types_of_Optimization_Programs/SOCPs.md",
    "Computer_Science/Information_Systems_Machine_Learning/EECS127AB/5_Types_of_Optimization_Programs/SOCPs.assets/image-20240124163859651.png",
    "Excalidraw/Drawing 2024-01-24 16.37.32.excalidraw.md",
    "Computer_Science/Information_Systems_Machine_Learning/EECS127AB/5_Types_of_Optimization_Programs/SOCPs.assets/image-20240124163122715.png",
    "Computer_Science/Information_Systems_Machine_Learning/EECS127AB/5_Types_of_Optimization_Programs/QCQPs.md",
    "Computer_Science/Information_Systems_Machine_Learning/EECS127AB/5_Types_of_Optimization_Programs/Quadratic_Programs.md",
    "Computer_Science/Information_Systems_Machine_Learning/EECS189/MLE&Multivariate Gaussian.md",
    "Computer_Science/Information_Systems_Machine_Learning/EECS189/Linear Regression.md",
    "Computer_Science/Data_Structures_Algorithms/CS106B_X/C++_Projects/Advanced_Programming/AP-HW5-Inheritance.md",
    "Computer_Science/Computer_Systems/Database Systems/UCB_CS186/Projects/Project0_Setup(Sp24).md",
    "Computer_Science/Computer_Systems/Database Systems/UCB_CS186/Projects/Project1_SQL(sp24).md",
    "Computer_Science/Computer_Systems/Database Systems/UCB_CS186/Lecture_Notes/5_Big_Data_Topics/MapReduce&Spark.md",
    "Computer_Science/Computer_Systems/Database Systems/UCB_CS186/Lecture_Notes/5_Big_Data_Topics/No_SQL.md",
    "Computer_Science/Computer_Systems/Database Systems/UCB_CS186/Lecture_Notes/4_DB_Design/Data_Replication.md",
    "Computer_Science/Computer_Systems/Database Systems/UCB_CS186/Lecture_Notes/4_DB_Design/DB_Design.md",
    "Computer_Science/Computer_Systems/Database Systems/UCB_CS186/Lecture_Notes/3_Transaction&Recovery/Recovery.md",
    "Computer_Science/Computer_Systems/Database Systems/UCB_CS186/Lecture_Notes/3_Transaction&Recovery/Transactions.md",
    "Computer_Science/Computer_Systems/Database Systems/UCB_CS186/Lecture_Notes/1_SQL_Algebra/Iterators&Joins.md",
    "Computer_Science/Computer_Systems/Database Systems/UCB_CS186/Lecture_Notes/1_SQL_Algebra/Query_Optimization.md",
    "Computer_Science/Computer_Systems/Database Systems/UCB_CS186/Lecture_Notes/1_SQL_Algebra/Sorting&Hashing.md",
    "Computer_Science/Computer_Systems/Database Systems/UCB_CS186/Lecture_Notes/1_SQL_Algebra/Relational_Algebra.md",
    "Computer_Science/Computer_Systems/Database Systems/UCB_CS186/Lecture_Notes/2_DBMS_Architecture/Buffer_Management.md",
    "Computer_Science/Computer_Systems/Database Systems/UCB_CS186/Lecture_Notes/2_DBMS_Architecture/File_Index_Management.md",
    "Computer_Science/Computer_Systems/Database Systems/UCB_CS186/Lecture_Notes/2_DBMS_Architecture/File_Index_Management.assets/image-20240124154245459.png",
    "Computer_Science/Computer_Systems/Database Systems/UCB_CS186/Lecture_Notes/2_DBMS_Architecture/File_Index_Management.assets/image-20240124154236433.png",
    "Computer_Science/Computer_Systems/Database Systems/UCB_CS186/Lecture_Notes/2_DBMS_Architecture/File_Index_Management.assets/image-20240124154228225.png",
    "Computer_Science/Computer_Systems/Database Systems/UCB_CS186/Lecture_Notes/2_DBMS_Architecture/File_Index_Management.assets/image-20240124154221859.png",
    "Computer_Science/Computer_Systems/Database Systems/UCB_CS186/Lecture_Notes/2_DBMS_Architecture/File_Index_Management.assets/image-20240124154204121.png",
    "Computer_Science/Computer_Systems/Database Systems/UCB_CS186/Lecture_Notes/2_DBMS_Architecture/File_Index_Management.assets/image-20240124154136305.png",
    "Computer_Science/Computer_Systems/Database Systems/UCB_CS186/Lecture_Notes/2_DBMS_Architecture/File_Index_Management.assets/image-20240124154127270.png",
    "Computer_Science/Computer_Systems/Database Systems/UCB_CS186/Lecture_Notes/2_DBMS_Architecture/File_Index_Management.assets/image-20240124154057353.png",
    "Mathematics/NYU_Master_Program/DS-GA-3001/Causal_Inference_in_Machine_Learning/Related_Resources.md",
    "Mathematics/NYU_Master_Program/DS-GA-3001/Causal_Inference_in_Machine_Learning/Lecture_1_2024_0112.md",
    "未命名.canvas"
  ]
}