{
  "main": {
    "id": "afc3fe0383aebaf5",
    "type": "split",
    "children": [
      {
        "id": "d2ff9fc76616f57b",
        "type": "tabs",
        "children": [
          {
            "id": "736aeb70201c5bf3",
            "type": "leaf",
            "state": {
              "type": "markdown",
              "state": {
                "file": "Computer_Science/Web_Development/前端项目/新闻头条.md",
                "mode": "source",
                "source": false
              }
            }
          },
          {
            "id": "d501f94fb35fb4d2",
            "type": "leaf",
            "state": {
              "type": "markdown",
              "state": {
                "file": "Computer_Science/Web_Development/Javascript/DOM/浏览器渲染原理.md",
                "mode": "source",
                "source": false
              }
            }
          },
          {
            "id": "1877bf3409c9be73",
            "type": "leaf",
            "state": {
              "type": "markdown",
              "state": {
                "file": "Computer_Science/Deep_Learning/Model_Compression/Parameter_Quantization.md",
                "mode": "source",
                "source": false
              }
            }
          },
          {
            "id": "3581f8a72e1daf2b",
            "type": "leaf",
            "state": {
              "type": "markdown",
              "state": {
                "file": "Computer_Science/Deep_Learning/Transformers/Transformer_Basics.md",
                "mode": "source",
                "source": false
              }
            }
          }
        ],
        "currentTab": 1
      }
    ],
    "direction": "vertical"
  },
  "left": {
    "id": "f900f31b8b407685",
    "type": "split",
    "children": [
      {
        "id": "ac58ecdddeed7005",
        "type": "tabs",
        "dimension": 75.84442169907881,
        "children": [
          {
            "id": "932953190040c9d5",
            "type": "leaf",
            "state": {
              "type": "file-explorer",
              "state": {
                "sortOrder": "alphabetical"
              }
            }
          },
          {
            "id": "a1ae5d442675c9de",
            "type": "leaf",
            "state": {
              "type": "search",
              "state": {
                "query": "deepCl",
                "matchingCase": false,
                "explainSearch": false,
                "collapseAll": false,
                "extraContext": false,
                "sortOrder": "alphabetical"
              }
            }
          },
          {
            "id": "f77f76cb311858e9",
            "type": "leaf",
            "state": {
              "type": "starred",
              "state": {}
            }
          },
          {
            "id": "eae0deb31a4dd2bb",
            "type": "leaf",
            "state": {
              "type": "bookmarks",
              "state": {}
            }
          }
        ]
      },
      {
        "id": "4f417f835f612f94",
        "type": "tabs",
        "dimension": 24.15557830092119,
        "children": [
          {
            "id": "f58fc5649c2dc1e2",
            "type": "leaf",
            "state": {
              "type": "recent-files",
              "state": {}
            }
          }
        ]
      }
    ],
    "direction": "horizontal",
    "width": 304.5
  },
  "right": {
    "id": "646448ef3be5aeb8",
    "type": "split",
    "children": [
      {
        "id": "a57d72b1463cfa44",
        "type": "tabs",
        "dimension": 28.823529411764707,
        "children": [
          {
            "id": "abd22396395eb00b",
            "type": "leaf",
            "state": {
              "type": "quiet-outline",
              "state": {}
            }
          },
          {
            "id": "2bfcad073fc70b2f",
            "type": "leaf",
            "state": {
              "type": "advanced-tables-toolbar",
              "state": {}
            }
          },
          {
            "id": "79ec672f363dd13b",
            "type": "leaf",
            "state": {
              "type": "mermaid-toolbar-view",
              "state": {}
            }
          }
        ]
      },
      {
        "id": "ac5e674590e10608",
        "type": "tabs",
        "dimension": 44.41176470588235,
        "children": [
          {
            "id": "83c7969190d88bc2",
            "type": "leaf",
            "state": {
              "type": "backlink",
              "state": {
                "file": "Computer_Science/Web_Development/Javascript/DOM/浏览器渲染原理.md",
                "collapseAll": false,
                "extraContext": false,
                "sortOrder": "alphabetical",
                "showSearch": false,
                "searchQuery": "",
                "backlinkCollapsed": false,
                "unlinkedCollapsed": true
              }
            }
          },
          {
            "id": "4b87139d7043d916",
            "type": "leaf",
            "state": {
              "type": "outgoing-link",
              "state": {
                "file": "Computer_Science/Web_Development/Javascript/DOM/浏览器渲染原理.md",
                "linksCollapsed": false,
                "unlinkedCollapsed": true
              }
            }
          }
        ],
        "currentTab": 1
      },
      {
        "id": "2349a3933801eec4",
        "type": "tabs",
        "dimension": 26.764705882352946,
        "children": [
          {
            "id": "06e519aa4232ea63",
            "type": "leaf",
            "state": {
              "type": "tag",
              "state": {
                "sortOrder": "frequency",
                "useHierarchy": true
              }
            }
          },
          {
            "id": "2ad6c65501c7e27e",
            "type": "leaf",
            "state": {
              "type": "calendar",
              "state": {}
            }
          }
        ],
        "currentTab": 1
      }
    ],
    "direction": "horizontal",
    "width": 334.5
  },
  "left-ribbon": {
    "hiddenItems": {
      "switcher:Open quick switcher": false,
      "graph:Open graph view": false,
      "canvas:Create new canvas": false,
      "daily-notes:Open today's daily note": false,
      "templates:Insert template": false,
      "command-palette:Open command palette": false,
      "workspaces:Manage workspace layouts": false,
      "obsidian-excalidraw-plugin:Create new drawing": false,
      "table-editor-obsidian:Advanced Tables Toolbar": false,
      "oz-clear-unused-images:Clear Unused Images": false,
      "obsidian-custom-frames:Open Notion": false,
      "obsidian-custom-frames:Open Google Calendar": false,
      "templater-obsidian:Templater": false,
      "mermaid-tools:Open Mermaid Toolbar": false,
      "obsidian-local-images-plus:Local Images Plus  0.15.9\r\nLocalize attachments (plugin folder)": false
    }
  },
  "active": "d501f94fb35fb4d2",
  "lastOpenFiles": [
    "Computer_Science/Web_Development/Javascript/DOM/浏览器渲染原理.assets/b2bb7cb5c462637cd035772e4f63ea82_MD5.jpeg",
    "Computer_Science/Web_Development/Javascript/DOM/浏览器渲染原理.assets/image-20241005130302077.png",
    "Computer_Science/Web_Development/Javascript/DOM/浏览器渲染原理.assets/364b8283c8a9c1d21261e06a274055aa_MD5.jpeg",
    "Computer_Science/Web_Development/Javascript/DOM/浏览器渲染原理.assets/image-20241005125824238.png",
    "Computer_Science/Web_Development/Javascript/DOM/浏览器渲染原理.assets/021eed575792663552671722078d8765_MD5.jpeg",
    "Computer_Science/Web_Development/Javascript/DOM/浏览器渲染原理.assets/image-20241005124138385.png",
    "Computer_Science/Web_Development/Javascript/DOM/事件循环.md",
    "Computer_Science/Web_Development/Javascript/DOM/事件循环.assets/56a4dda604d014dd1c6d59dee175191b_MD5.jpeg",
    "Computer_Science/Web_Development/Javascript/DOM/事件循环.assets/c57580451a7a48df2f115888b79be1ba_MD5.jpeg",
    "Computer_Science/Web_Development/Javascript/DOM/事件循环.assets/image-20241005121336691.png",
    "Computer_Science/Web_Development/Javascript/DOM/事件循环.assets/image-20241005121324790.png",
    "Computer_Science/Web_Development/Javascript/DOM/事件循环.assets/333b8226fa62e152fd2c5e4f442f8e22_MD5.jpeg",
    "Computer_Science/Web_Development/Javascript/DOM/事件循环.assets",
    "Computer_Science/Web_Development/Javascript/DOM/浏览器渲染原理.md",
    "Computer_Science/Web_Development/Javascript/DOM/浏览器渲染原理.assets",
    "Computer_Science/Web_Development/Javascript/异步提升/并发控制.md",
    "Computer_Science/Web_Development/Javascript/异步提升/r.md",
    "Computer_Science/Web_Development/Javascript/总结/总结：this指向总结.md",
    "Computer_Science/Web_Development/Javascript/函数/作用域.md",
    "Computer_Science/Web_Development/Javascript/函数/作用域.assets",
    "Computer_Science/Web_Development/HTMLCSS/常用需求实现/轮播图.md",
    "Computer_Science/Web_Development/前端项目/新闻头条.md",
    "Computer_Science/Web_Development/前端测试和调试/Vitest.md",
    "Computer_Science/Web_Development/前端项目",
    "Computer_Science/Deep_Learning/Model_Compression/Parameter_Quantization.md",
    "Computer_Science/Natural_Language_Processing/Pre-Post-training/Finetuning.md",
    "Computer_Science/Deep_Learning/Model_Compression",
    "Computer_Science/Natural_Language_Processing/Pre-Post-training/Finetuning_Examples.md",
    "Computer_Science/Deep_Learning/Transformers/Transformer_Basics.md",
    "Computer_Science/Web_Development/Javascript/Functional_Programming/Debouncing.md",
    "Computer_Science/Web_Development/Javascript/Promise/Promise重写.md",
    "Computer_Science/Web_Development/前端测试和调试/Console调试.md",
    "Computer_Science/Web_Development/前端测试和调试/Console调试.assets",
    "Computer_Science/Web_Development/HTMLCSS/常用需求实现/滚动元素到可视区域.md",
    "Computer_Science/Web_Development/Javascript/对象/Property和Element.md",
    "Computer_Science/Web_Development/前端测试和调试/Vitest.assets",
    "Computer_Science/Web_Development/Javascript/对象/P9_构造函数及实例化原理_包装类.md",
    "Computer_Science/Web_Development/Javascript/对象/P8_对象_构造函数_实例化.md",
    "Computer_Science/Web_Development/HTMLCSS/常用需求实现/进度条.md",
    "Computer_Science/Web_Development/Javascript/对象/未确认 668208.crdownload",
    "Computer_Science/Web_Development/Javascript/对象/P9_构造函数及实例化原理_包装类.docx",
    "Computer_Science/Web_Development/Javascript/对象/未确认 976283.crdownload",
    "Computer_Science/Web_Development/HTMLCSS/常用需求实现/文本溢出隐藏.md",
    "Computer_Science/Web_Development/HTMLCSS/常用需求实现/圆角渐变边框.md",
    "Computer_Science/Web_Development/Javascript/实用函数/Useful_Functions.md",
    "Computer_Science/Web_Development/Javascript/实用函数/兼容性封装汇总.md",
    "未命名.canvas"
  ]
}